dynamic_bitmap/__init__.py
dynamic_bitmap/bitmap.py
dynamic_bitmap/segmented_bitmap.py
dynamic_bitmap/utils.py
dynamic_bitmap/ai/__init__.py
dynamic_bitmap/ai/dataset.py
dynamic_bitmap/ai/features.py
dynamic_bitmap/ai/model.py
dynamic_bitmap/ai/predictor.py
dynamic_bitmap/p2p/__init__.py
dynamic_bitmap/p2p/dpb_net.py
dynamic_bitmap/p2p/dpb_net_q.py
dynamic_bitmap-0.3.3.dist-info/METADATA
dynamic_bitmap-0.3.3.dist-info/WHEEL
dynamic_bitmap-0.3.3.dist-info/top_level.txt
dynamic_bitmap-0.3.3.dist-info/RECORD
