Metadata-Version: 2.4
Name: dynamic-bitmap
Version: 0.3.3
Summary: Dynamic Parallel Bitmap con soporte de IA para búsquedas optimizadas, ahora con una vision sobre la conexion p2p.
Home-page: https://github.com/JesusDeg8061/Dynamic_bitmap
Author: Jesus Alberto Degollado Lopez
Author-email: jesuslopez5587@gmail.com
Classifier: Programming Language :: Python :: 3
Classifier: License :: OSI Approved :: MIT License
Classifier: Operating System :: OS Independent
Classifier: Topic :: Scientific/Engineering :: Artificial Intelligence
Classifier: Topic :: Software Development :: Libraries :: Python Modules
Requires-Python: >=3.8
Requires-Dist: numpy>=1.21
Requires-Dist: tensorflow>=2.11
Requires-Dist: scikit-learn>=1.0
Dynamic: author
Dynamic: author-email
Dynamic: classifier
Dynamic: description
Dynamic: description-content-type
Dynamic: home-page
Dynamic: requires-dist
Dynamic: requires-python
Dynamic: summary
